{"template":"__react_static_root__/src/containers/PropertyDetails","sharedHashesByProp":{},"data":{"property":{"id":124,"createdWAt":"2020-05-22T08:38:38.582Z","updatedWAt":"2020-05-22T09:48:14.557Z","agency_id":35,"area":1000,"available_from":"2020-05-23T08:18:25.000Z","bathrooms":1,"bedrooms":1,"city":"","country":"","housing_type":"family_house","deleted":false,"description":"trtytrytryrty","interior":false,"latitude":"40.69830339999999","longitude":"-73.9888406","parking_place":false,"price":650,"publication_date":null,"published":true,"state":"","street_address":"","title":"Family house Elite","utilities":false,"zip_code":"","property_images":[{"id":6,"createdWAt":"2020-05-22T08:59:15.030Z","updatedWAt":"2020-05-22T09:48:14.553Z","image":"https://real-estate-node-bucket.s3.eu-central-1.amazonaws.com/1590137954611-124.jpeg","main_image":true,"property_id":124},{"id":4,"createdWAt":"2020-05-22T08:59:15.013Z","updatedWAt":"2020-05-22T08:59:15.013Z","image":"https://real-estate-node-bucket.s3.eu-central-1.amazonaws.com/1590137954025-124.jpeg","main_image":false,"property_id":124},{"id":7,"createdWAt":"2020-05-22T08:59:15.037Z","updatedWAt":"2020-05-22T08:59:15.037Z","image":"https://real-estate-node-bucket.s3.eu-central-1.amazonaws.com/1590137954797-124.jpeg","main_image":false,"property_id":124},{"id":5,"createdWAt":"2020-05-22T08:59:15.024Z","updatedWAt":"2020-05-22T08:59:15.024Z","image":"https://real-estate-node-bucket.s3.eu-central-1.amazonaws.com/1590137954321-124.jpeg","main_image":false,"property_id":124}]}},"path":"properties/property/124"}
